[
    {
        "id": "thorn_strike",
        "name": "Thorn Strike",
        "iconID": "actorconditions_1:0",
        "isNegative": 1,
        "abilityEffect": {
            "increaseAttackChance": 15,
            "increaseAttackDamage": {
                "min": 10,
                "max": 25
            }
        }
    },
    {
        "id": "poison_bloom",
        "name": "Poison Bloom",
        "iconID": "actorconditions_1:0",
        "isNegative": 1,
        "abilityEffect": {
            "increaseAttackChance": 15,
            "increaseAttackDamage": {
                "min": 10,
                "max": 25
            }
        }
    },
    {
        "id": "natures_wrath",
        "name": "Natures Wrath",
        "iconID": "actorconditions_1:0",
        "isNegative": 1,
        "abilityEffect": {
            "increaseAttackChance": 15,
            "increaseAttackDamage": {
                "min": 10,
                "max": 25
            }
        }
    },
    {
        "id": "vine_lash",
        "name": "Vine Lash",
        "iconID": "actorconditions_1:0",
        "isNegative": 1,
        "abilityEffect": {
            "increaseAttackChance": 15,
            "increaseAttackDamage": {
                "min": 10,
                "max": 25
            }
        }
    },
    {
        "id": "earthquake",
        "name": "Earthquake",
        "iconID": "actorconditions_1:0",
        "isNegative": 1,
        "abilityEffect": {
            "increaseAttackChance": 15,
            "increaseAttackDamage": {
                "min": 10,
                "max": 25
            }
        }
    },
    {
        "id": "hurricane",
        "name": "Hurricane",
        "iconID": "actorconditions_1:0",
        "isNegative": 1,
        "abilityEffect": {
            "increaseAttackChance": 15,
            "increaseAttackDamage": {
                "min": 10,
                "max": 25
            }
        }
    },
    {
        "id": "wildfire",
        "name": "Wildfire",
        "iconID": "actorconditions_1:0",
        "isNegative": 1,
        "abilityEffect": {
            "increaseAttackChance": 15,
            "increaseAttackDamage": {
                "min": 10,
                "max": 25
            }
        }
    },
    {
        "id": "storm_call",
        "name": "Storm Call",
        "iconID": "actorconditions_1:0",
        "isNegative": 1,
        "abilityEffect": {
            "increaseAttackChance": 15,
            "increaseAttackDamage": {
                "min": 10,
                "max": 25
            }
        }
    },
    {
        "id": "venom_roots",
        "name": "Venom Roots",
        "iconID": "actorconditions_1:0",
        "isNegative": 1,
        "abilityEffect": {
            "increaseAttackChance": 15,
            "increaseAttackDamage": {
                "min": 10,
                "max": 25
            }
        }
    },
    {
        "id": "moonfire",
        "name": "Moonfire",
        "iconID": "actorconditions_1:0",
        "isNegative": 1,
        "abilityEffect": {
            "increaseAttackChance": 15,
            "increaseAttackDamage": {
                "min": 10,
                "max": 25
            }
        }
    },
    {
        "id": "sunstrike",
        "name": "Sunstrike",
        "iconID": "actorconditions_1:0",
        "isNegative": 1,
        "abilityEffect": {
            "increaseAttackChance": 15,
            "increaseAttackDamage": {
                "min": 10,
                "max": 25
            }
        }
    },
    {
        "id": "entangle",
        "name": "Entangle",
        "iconID": "actorconditions_1:0",
        "isNegative": 1,
        "abilityEffect": {
            "increaseAttackChance": 15,
            "increaseAttackDamage": {
                "min": 10,
                "max": 25
            }
        }
    },
    {
        "id": "nature_bolt",
        "name": "Nature Bolt",
        "iconID": "actorconditions_1:0",
        "isNegative": 1,
        "abilityEffect": {
            "increaseAttackChance": 15,
            "increaseAttackDamage": {
                "min": 10,
                "max": 25
            }
        }
    },
    {
        "id": "oak_smash",
        "name": "Oak Smash",
        "iconID": "actorconditions_1:0",
        "isNegative": 1,
        "abilityEffect": {
            "increaseAttackChance": 15,
            "increaseAttackDamage": {
                "min": 10,
                "max": 25
            }
        }
    },
    {
        "id": "tornado",
        "name": "Tornado",
        "iconID": "actorconditions_1:0",
        "isNegative": 1,
        "abilityEffect": {
            "increaseAttackChance": 15,
            "increaseAttackDamage": {
                "min": 10,
                "max": 25
            }
        }
    },
    {
        "id": "spirit_thorn",
        "name": "Spirit Thorn",
        "iconID": "actorconditions_1:0",
        "isNegative": 1,
        "abilityEffect": {
            "increaseAttackChance": 15,
            "increaseAttackDamage": {
                "min": 10,
                "max": 25
            }
        }
    },
    {
        "id": "feral_rage",
        "name": "Feral Rage",
        "iconID": "actorconditions_1:0",
        "isNegative": 1,
        "abilityEffect": {
            "increaseAttackChance": 15,
            "increaseAttackDamage": {
                "min": 10,
                "max": 25
            }
        }
    },
    {
        "id": "earth_spear",
        "name": "Earth Spear",
        "iconID": "actorconditions_1:0",
        "isNegative": 1,
        "abilityEffect": {
            "increaseAttackChance": 15,
            "increaseAttackDamage": {
                "min": 10,
                "max": 25
            }
        }
    },
    {
        "id": "bloom_rot",
        "name": "Bloom Rot",
        "iconID": "actorconditions_1:0",
        "isNegative": 1,
        "abilityEffect": {
            "increaseAttackChance": 15,
            "increaseAttackDamage": {
                "min": 10,
                "max": 25
            }
        }
    },
    {
        "id": "nature_shock",
        "name": "Nature Shock",
        "iconID": "actorconditions_1:0",
        "isNegative": 1,
        "abilityEffect": {
            "increaseAttackChance": 15,
            "increaseAttackDamage": {
                "min": 10,
                "max": 25
            }
        }
    },
    {
        "id": "wild_growth",
        "name": "Wild Growth",
        "iconID": "actorconditions_1:0",
        "isNegative": 1,
        "abilityEffect": {
            "increaseAttackChance": 15,
            "increaseAttackDamage": {
                "min": 10,
                "max": 25
            }
        }
    },
    {
        "id": "forest_fury",
        "name": "Forest Fury",
        "iconID": "actorconditions_1:0",
        "isNegative": 1,
        "abilityEffect": {
            "increaseAttackChance": 15,
            "increaseAttackDamage": {
                "min": 10,
                "max": 25
            }
        }
    },
    {
        "id": "plague_seeds",
        "name": "Plague Seeds",
        "iconID": "actorconditions_1:0",
        "isNegative": 1,
        "abilityEffect": {
            "increaseAttackChance": 15,
            "increaseAttackDamage": {
                "min": 10,
                "max": 25
            }
        }
    },
    {
        "id": "stone_rain",
        "name": "Stone Rain",
        "iconID": "actorconditions_1:0",
        "isNegative": 1,
        "abilityEffect": {
            "increaseAttackChance": 15,
            "increaseAttackDamage": {
                "min": 10,
                "max": 25
            }
        }
    },
    {
        "id": "wrath_of_beasts",
        "name": "Wrath of Beasts",
        "iconID": "actorconditions_1:0",
        "isNegative": 1,
        "abilityEffect": {
            "increaseAttackChance": 15,
            "increaseAttackDamage": {
                "min": 10,
                "max": 25
            }
        }
    },
    {
        "id": "barkskin",
        "name": "Barkskin",
        "iconID": "actorconditions_1:0",
        "isNegative": 0,
        "abilityEffect": {
            "increaseDefense": 15,
            "increaseMaxHP": 25
        }
    },
    {
        "id": "nature_shield",
        "name": "Nature Shield",
        "iconID": "actorconditions_1:0",
        "isNegative": 0,
        "abilityEffect": {
            "increaseDefense": 15,
            "increaseMaxHP": 25
        }
    },
    {
        "id": "regrowth",
        "name": "Regrowth",
        "iconID": "actorconditions_1:0",
        "isNegative": 0,
        "abilityEffect": {
            "increaseDefense": 15,
            "increaseMaxHP": 25
        }
    },
    {
        "id": "spirit_guard",
        "name": "Spirit Guard",
        "iconID": "actorconditions_1:0",
        "isNegative": 0,
        "abilityEffect": {
            "increaseDefense": 15,
            "increaseMaxHP": 25
        }
    },
    {
        "id": "earth_ward",
        "name": "Earth Ward",
        "iconID": "actorconditions_1:0",
        "isNegative": 0,
        "abilityEffect": {
            "increaseDefense": 15,
            "increaseMaxHP": 25
        }
    },
    {
        "id": "stone_skin",
        "name": "Stone Skin",
        "iconID": "actorconditions_1:0",
        "isNegative": 0,
        "abilityEffect": {
            "increaseDefense": 15,
            "increaseMaxHP": 25
        }
    },
    {
        "id": "healing_roots",
        "name": "Healing Roots",
        "iconID": "actorconditions_1:0",
        "isNegative": 0,
        "abilityEffect": {
            "increaseDefense": 15,
            "increaseMaxHP": 25
        }
    },
    {
        "id": "wild_protection",
        "name": "Wild Protection",
        "iconID": "actorconditions_1:0",
        "isNegative": 0,
        "abilityEffect": {
            "increaseDefense": 15,
            "increaseMaxHP": 25
        }
    },
    {
        "id": "moon_ward",
        "name": "Moon Ward",
        "iconID": "actorconditions_1:0",
        "isNegative": 0,
        "abilityEffect": {
            "increaseDefense": 15,
            "increaseMaxHP": 25
        }
    },
    {
        "id": "forest_veil",
        "name": "Forest Veil",
        "iconID": "actorconditions_1:0",
        "isNegative": 0,
        "abilityEffect": {
            "increaseDefense": 15,
            "increaseMaxHP": 25
        }
    },
    {
        "id": "natural_armor",
        "name": "Natural Armor",
        "iconID": "actorconditions_1:0",
        "isNegative": 0,
        "abilityEffect": {
            "increaseDefense": 15,
            "increaseMaxHP": 25
        }
    },
    {
        "id": "oak_shield",
        "name": "Oak Shield",
        "iconID": "actorconditions_1:0",
        "isNegative": 0,
        "abilityEffect": {
            "increaseDefense": 15,
            "increaseMaxHP": 25
        }
    },
    {
        "id": "nature_blessing",
        "name": "Nature Blessing",
        "iconID": "actorconditions_1:0",
        "isNegative": 0,
        "abilityEffect": {
            "increaseDefense": 15,
            "increaseMaxHP": 25
        }
    },
    {
        "id": "renewal",
        "name": "Renewal",
        "iconID": "actorconditions_1:0",
        "isNegative": 0,
        "abilityEffect": {
            "increaseDefense": 15,
            "increaseMaxHP": 25
        }
    },
    {
        "id": "lifebloom",
        "name": "Lifebloom",
        "iconID": "actorconditions_1:0",
        "isNegative": 0,
        "abilityEffect": {
            "increaseDefense": 15,
            "increaseMaxHP": 25
        }
    },
    {
        "id": "ancient_ward",
        "name": "Ancient Ward",
        "iconID": "actorconditions_1:0",
        "isNegative": 0,
        "abilityEffect": {
            "increaseDefense": 15,
            "increaseMaxHP": 25
        }
    },
    {
        "id": "storm_barrier",
        "name": "Storm Barrier",
        "iconID": "actorconditions_1:0",
        "isNegative": 0,
        "abilityEffect": {
            "increaseDefense": 15,
            "increaseMaxHP": 25
        }
    },
    {
        "id": "wild_grace",
        "name": "Wild Grace",
        "iconID": "actorconditions_1:0",
        "isNegative": 0,
        "abilityEffect": {
            "increaseDefense": 15,
            "increaseMaxHP": 25
        }
    },
    {
        "id": "spirit_bark",
        "name": "Spirit Bark",
        "iconID": "actorconditions_1:0",
        "isNegative": 0,
        "abilityEffect": {
            "increaseDefense": 15,
            "increaseMaxHP": 25
        }
    },
    {
        "id": "earth_guard",
        "name": "Earth Guard",
        "iconID": "actorconditions_1:0",
        "isNegative": 0,
        "abilityEffect": {
            "increaseDefense": 15,
            "increaseMaxHP": 25
        }
    },
    {
        "id": "feral_shield",
        "name": "Feral Shield",
        "iconID": "actorconditions_1:0",
        "isNegative": 0,
        "abilityEffect": {
            "increaseDefense": 15,
            "increaseMaxHP": 25
        }
    },
    {
        "id": "bloom_shield",
        "name": "Bloom Shield",
        "iconID": "actorconditions_1:0",
        "isNegative": 0,
        "abilityEffect": {
            "increaseDefense": 15,
            "increaseMaxHP": 25
        }
    },
    {
        "id": "root_barrier",
        "name": "Root Barrier",
        "iconID": "actorconditions_1:0",
        "isNegative": 0,
        "abilityEffect": {
            "increaseDefense": 15,
            "increaseMaxHP": 25
        }
    },
    {
        "id": "nature_sanctuary",
        "name": "Nature Sanctuary",
        "iconID": "actorconditions_1:0",
        "isNegative": 0,
        "abilityEffect": {
            "increaseDefense": 15,
            "increaseMaxHP": 25
        }
    },
    {
        "id": "beast_ward",
        "name": "Beast Ward",
        "iconID": "actorconditions_1:0",
        "isNegative": 0,
        "abilityEffect": {
            "increaseDefense": 15,
            "increaseMaxHP": 25
        }
    }
]