{
  "dropLists": [
    {
      "id": "drop_human_common",
      "items": [
        {
          "itemID": "healing_herb",
          "chance": 30,
          "min": 1,
          "max": 2
        }
      ],
      "gold": {
        "min": 7,
        "max": 30
      }
    },
    {
      "id": "drop_human_leader",
      "items": [
        {
          "itemID": "healing_herb",
          "chance": 50,
          "min": 2,
          "max": 4
        },
        {
          "itemID": "supplies_human",
          "chance": 20,
          "min": 1,
          "max": 1
        }
      ],
      "gold": {
        "min": 30,
        "max": 90
      }
    },
    {
      "id": "drop_halfelf_common",
      "items": [
        {
          "itemID": "healing_herb",
          "chance": 30,
          "min": 1,
          "max": 2
        }
      ],
      "gold": {
        "min": 7,
        "max": 28
      }
    },
    {
      "id": "drop_halfelf_leader",
      "items": [
        {
          "itemID": "healing_herb",
          "chance": 50,
          "min": 2,
          "max": 4
        },
        {
          "itemID": "healing_herb",
          "chance": 20,
          "min": 1,
          "max": 1
        }
      ],
      "gold": {
        "min": 28,
        "max": 84
      }
    },
    {
      "id": "drop_elf_common",
      "items": [
        {
          "itemID": "healing_herb",
          "chance": 30,
          "min": 1,
          "max": 2
        }
      ],
      "gold": {
        "min": 9,
        "max": 36
      }
    },
    {
      "id": "drop_elf_leader",
      "items": [
        {
          "itemID": "healing_herb",
          "chance": 50,
          "min": 2,
          "max": 4
        },
        {
          "itemID": "healing_herb",
          "chance": 20,
          "min": 1,
          "max": 1
        }
      ],
      "gold": {
        "min": 36,
        "max": 108
      }
    },
    {
      "id": "drop_woodelf_common",
      "items": [
        {
          "itemID": "healing_herb",
          "chance": 30,
          "min": 1,
          "max": 2
        }
      ],
      "gold": {
        "min": 8,
        "max": 32
      }
    },
    {
      "id": "drop_woodelf_leader",
      "items": [
        {
          "itemID": "healing_herb",
          "chance": 50,
          "min": 2,
          "max": 4
        },
        {
          "itemID": "healing_herb",
          "chance": 20,
          "min": 1,
          "max": 1
        }
      ],
      "gold": {
        "min": 32,
        "max": 96
      }
    },
    {
      "id": "drop_drowelf_common",
      "items": [
        {
          "itemID": "healing_herb",
          "chance": 30,
          "min": 1,
          "max": 2
        }
      ],
      "gold": {
        "min": 10,
        "max": 40
      }
    },
    {
      "id": "drop_drowelf_leader",
      "items": [
        {
          "itemID": "healing_herb",
          "chance": 50,
          "min": 2,
          "max": 4
        },
        {
          "itemID": "healing_herb",
          "chance": 20,
          "min": 1,
          "max": 1
        }
      ],
      "gold": {
        "min": 40,
        "max": 120
      }
    },
    {
      "id": "drop_seaelf_common",
      "items": [
        {
          "itemID": "healing_herb",
          "chance": 30,
          "min": 1,
          "max": 2
        }
      ],
      "gold": {
        "min": 8,
        "max": 32
      }
    },
    {
      "id": "drop_seaelf_leader",
      "items": [
        {
          "itemID": "healing_herb",
          "chance": 50,
          "min": 2,
          "max": 4
        },
        {
          "itemID": "healing_herb",
          "chance": 20,
          "min": 1,
          "max": 1
        }
      ],
      "gold": {
        "min": 32,
        "max": 96
      }
    },
    {
      "id": "drop_dwarf_common",
      "items": [
        {
          "itemID": "healing_herb",
          "chance": 30,
          "min": 1,
          "max": 2
        }
      ],
      "gold": {
        "min": 9,
        "max": 36
      }
    },
    {
      "id": "drop_dwarf_leader",
      "items": [
        {
          "itemID": "healing_herb",
          "chance": 50,
          "min": 2,
          "max": 4
        },
        {
          "itemID": "healing_herb",
          "chance": 20,
          "min": 1,
          "max": 1
        }
      ],
      "gold": {
        "min": 36,
        "max": 108
      }
    },
    {
      "id": "drop_goblin_common",
      "items": [
        {
          "itemID": "healing_herb",
          "chance": 30,
          "min": 1,
          "max": 2
        }
      ],
      "gold": {
        "min": 4,
        "max": 16
      }
    },
    {
      "id": "drop_goblin_leader",
      "items": [
        {
          "itemID": "healing_herb",
          "chance": 50,
          "min": 2,
          "max": 4
        },
        {
          "itemID": "healing_herb",
          "chance": 20,
          "min": 1,
          "max": 1
        }
      ],
      "gold": {
        "min": 16,
        "max": 48
      }
    },
    {
      "id": "drop_hobgoblin_common",
      "items": [
        {
          "itemID": "healing_herb",
          "chance": 30,
          "min": 1,
          "max": 2
        }
      ],
      "gold": {
        "min": 7,
        "max": 28
      }
    },
    {
      "id": "drop_hobgoblin_leader",
      "items": [
        {
          "itemID": "healing_herb",
          "chance": 50,
          "min": 2,
          "max": 4
        },
        {
          "itemID": "healing_herb",
          "chance": 20,
          "min": 1,
          "max": 1
        }
      ],
      "gold": {
        "min": 28,
        "max": 84
      }
    },
    {
      "id": "drop_gnome_common",
      "items": [
        {
          "itemID": "healing_herb",
          "chance": 30,
          "min": 1,
          "max": 2
        }
      ],
      "gold": {
        "min": 5,
        "max": 20
      }
    },
    {
      "id": "drop_gnome_leader",
      "items": [
        {
          "itemID": "healing_herb",
          "chance": 50,
          "min": 2,
          "max": 4
        },
        {
          "itemID": "healing_herb",
          "chance": 20,
          "min": 1,
          "max": 1
        }
      ],
      "gold": {
        "min": 20,
        "max": 60
      }
    },
    {
      "id": "drop_orc_common",
      "items": [
        {
          "itemID": "healing_herb",
          "chance": 30,
          "min": 1,
          "max": 2
        }
      ],
      "gold": {
        "min": 10,
        "max": 40
      }
    },
    {
      "id": "drop_orc_leader",
      "items": [
        {
          "itemID": "healing_herb",
          "chance": 50,
          "min": 2,
          "max": 4
        },
        {
          "itemID": "healing_herb",
          "chance": 20,
          "min": 1,
          "max": 1
        }
      ],
      "gold": {
        "min": 40,
        "max": 120
      }
    },
    {
      "id": "drop_ogre_common",
      "items": [
        {
          "itemID": "healing_herb",
          "chance": 30,
          "min": 1,
          "max": 2
        }
      ],
      "gold": {
        "min": 15,
        "max": 60
      }
    },
    {
      "id": "drop_ogre_leader",
      "items": [
        {
          "itemID": "healing_herb",
          "chance": 50,
          "min": 2,
          "max": 4
        },
        {
          "itemID": "healing_herb",
          "chance": 20,
          "min": 1,
          "max": 1
        }
      ],
      "gold": {
        "min": 60,
        "max": 180
      }
    },
    {
      "id": "drop_halfling_common",
      "items": [
        {
          "itemID": "healing_herb",
          "chance": 30,
          "min": 1,
          "max": 2
        }
      ],
      "gold": {
        "min": 4,
        "max": 16
      }
    },
    {
      "id": "drop_halfling_leader",
      "items": [
        {
          "itemID": "healing_herb",
          "chance": 50,
          "min": 2,
          "max": 4
        },
        {
          "itemID": "healing_herb",
          "chance": 20,
          "min": 1,
          "max": 1
        }
      ],
      "gold": {
        "min": 16,
        "max": 48
      }
    },
    {
      "id": "drop_dragon_common",
      "items": [
        {
          "itemID": "healing_herb",
          "chance": 30,
          "min": 1,
          "max": 2
        }
      ],
      "gold": {
        "min": 50,
        "max": 200
      }
    },
    {
      "id": "drop_dragon_leader",
      "items": [
        {
          "itemID": "healing_herb",
          "chance": 50,
          "min": 2,
          "max": 4
        },
        {
          "itemID": "healing_herb",
          "chance": 20,
          "min": 1,
          "max": 1
        }
      ],
      "gold": {
        "min": 200,
        "max": 600
      }
    },
    {
      "id": "drop_tournament_champion",
      "items": [
        {
          "itemID": "champions_medallion",
          "chance": 100,
          "min": 1,
          "max": 1
        }
      ],
      "gold": {
        "min": 500,
        "max": 1000
      }
    }
  ]
}