[
    {
        "id": "light_drow_1",
        "name": "Light Drow Warlock",
        "iconID": "monsters_arulirs:1",
        "maxHP": 191,
        "attackChance": 76,
        "attackDamage": {
            "min": 19,
            "max": 47
        },
        "moveCost": 3,
        "attackCost": 4,
        "droplistID": "droplist_light_1",
        "spawnGroup": "light_drow",
        "faction": "drow_elf"
    },
    {
        "id": "light_drow_2",
        "name": "Light Drow Beastmaster",
        "iconID": "monsters_arulirs:1",
        "maxHP": 599,
        "attackChance": 88,
        "attackDamage": {
            "min": 8,
            "max": 30
        },
        "moveCost": 5,
        "attackCost": 4,
        "droplistID": "droplist_light_2",
        "spawnGroup": "light_drow",
        "faction": "drow_elf"
    },
    {
        "id": "light_drow_3",
        "name": "Light Drow Witch",
        "iconID": "monsters_arulirs:1",
        "maxHP": 160,
        "attackChance": 63,
        "attackDamage": {
            "min": 18,
            "max": 41
        },
        "moveCost": 6,
        "attackCost": 8,
        "droplistID": "droplist_light_3",
        "spawnGroup": "light_drow",
        "faction": "drow_elf"
    },
    {
        "id": "light_drow_4",
        "name": "Light Drow Beastmaster",
        "iconID": "monsters_arulirs:1",
        "maxHP": 246,
        "attackChance": 55,
        "attackDamage": {
            "min": 22,
            "max": 45
        },
        "moveCost": 8,
        "attackCost": 4,
        "droplistID": "droplist_light_4",
        "spawnGroup": "light_drow",
        "faction": "drow_elf"
    },
    {
        "id": "light_drow_5",
        "name": "Light Drow Sorcerer",
        "iconID": "monsters_arulirs:1",
        "maxHP": 587,
        "attackChance": 82,
        "attackDamage": {
            "min": 9,
            "max": 20
        },
        "moveCost": 7,
        "attackCost": 3,
        "droplistID": "droplist_light_5",
        "spawnGroup": "light_drow",
        "faction": "drow_elf"
    },
    {
        "id": "light_drow_6",
        "name": "Light Drow Dark Cleric",
        "iconID": "monsters_arulirs:1",
        "maxHP": 412,
        "attackChance": 77,
        "attackDamage": {
            "min": 5,
            "max": 34
        },
        "moveCost": 7,
        "attackCost": 8,
        "droplistID": "droplist_light_6",
        "spawnGroup": "light_drow",
        "faction": "drow_elf"
    },
    {
        "id": "light_drow_7",
        "name": "Light Drow Executioner",
        "iconID": "monsters_arulirs:1",
        "maxHP": 256,
        "attackChance": 89,
        "attackDamage": {
            "min": 19,
            "max": 38
        },
        "moveCost": 3,
        "attackCost": 4,
        "droplistID": "droplist_light_7",
        "spawnGroup": "light_drow",
        "faction": "drow_elf"
    },
    {
        "id": "light_drow_8",
        "name": "Light Drow Poisoner",
        "iconID": "monsters_arulirs:1",
        "maxHP": 320,
        "attackChance": 53,
        "attackDamage": {
            "min": 23,
            "max": 53
        },
        "moveCost": 3,
        "attackCost": 3,
        "droplistID": "droplist_light_8",
        "spawnGroup": "light_drow",
        "faction": "drow_elf"
    },
    {
        "id": "light_drow_9",
        "name": "Light Drow Webspinner",
        "iconID": "monsters_arulirs:1",
        "maxHP": 222,
        "attackChance": 63,
        "attackDamage": {
            "min": 9,
            "max": 37
        },
        "moveCost": 4,
        "attackCost": 5,
        "droplistID": "droplist_light_9",
        "spawnGroup": "light_drow",
        "faction": "drow_elf"
    },
    {
        "id": "light_drow_10",
        "name": "Light Drow Sorcerer",
        "iconID": "monsters_arulirs:1",
        "maxHP": 383,
        "attackChance": 73,
        "attackDamage": {
            "min": 25,
            "max": 33
        },
        "moveCost": 4,
        "attackCost": 7,
        "droplistID": "droplist_light_10",
        "spawnGroup": "light_drow",
        "faction": "drow_elf"
    },
    {
        "id": "light_drow_11",
        "name": "Light Drow Tunnel Scout",
        "iconID": "monsters_arulirs:1",
        "maxHP": 512,
        "attackChance": 64,
        "attackDamage": {
            "min": 18,
            "max": 42
        },
        "moveCost": 6,
        "attackCost": 8,
        "droplistID": "droplist_light_11",
        "spawnGroup": "light_drow",
        "faction": "drow_elf"
    },
    {
        "id": "light_drow_12",
        "name": "Light Drow Crypt Stalker",
        "iconID": "monsters_arulirs:1",
        "maxHP": 437,
        "attackChance": 79,
        "attackDamage": {
            "min": 6,
            "max": 29
        },
        "moveCost": 8,
        "attackCost": 3,
        "droplistID": "droplist_light_12",
        "spawnGroup": "light_drow",
        "faction": "drow_elf"
    },
    {
        "id": "light_drow_13",
        "name": "Light Drow Guard",
        "iconID": "monsters_arulirs:1",
        "maxHP": 519,
        "attackChance": 89,
        "attackDamage": {
            "min": 17,
            "max": 31
        },
        "moveCost": 7,
        "attackCost": 7,
        "droplistID": "droplist_light_13",
        "spawnGroup": "light_drow",
        "faction": "drow_elf"
    },
    {
        "id": "light_drow_14",
        "name": "Light Drow Hunter",
        "iconID": "monsters_arulirs:1",
        "maxHP": 293,
        "attackChance": 63,
        "attackDamage": {
            "min": 6,
            "max": 20
        },
        "moveCost": 8,
        "attackCost": 6,
        "droplistID": "droplist_light_14",
        "spawnGroup": "light_drow",
        "faction": "drow_elf"
    },
    {
        "id": "light_drow_15",
        "name": "Light Drow Spider Tamer",
        "iconID": "monsters_arulirs:1",
        "maxHP": 559,
        "attackChance": 55,
        "attackDamage": {
            "min": 10,
            "max": 21
        },
        "moveCost": 4,
        "attackCost": 3,
        "droplistID": "droplist_light_15",
        "spawnGroup": "light_drow",
        "faction": "drow_elf"
    },
    {
        "id": "light_drow_16",
        "name": "Light Drow Mage",
        "iconID": "monsters_arulirs:1",
        "maxHP": 516,
        "attackChance": 77,
        "attackDamage": {
            "min": 24,
            "max": 37
        },
        "moveCost": 8,
        "attackCost": 6,
        "droplistID": "droplist_light_16",
        "spawnGroup": "light_drow",
        "faction": "drow_elf"
    },
    {
        "id": "light_drow_17",
        "name": "Light Drow Champion",
        "iconID": "monsters_arulirs:1",
        "maxHP": 229,
        "attackChance": 80,
        "attackDamage": {
            "min": 9,
            "max": 22
        },
        "moveCost": 6,
        "attackCost": 5,
        "droplistID": "droplist_light_17",
        "spawnGroup": "light_drow",
        "faction": "drow_elf"
    },
    {
        "id": "light_drow_18",
        "name": "Light Drow Crypt Stalker",
        "iconID": "monsters_arulirs:1",
        "maxHP": 477,
        "attackChance": 70,
        "attackDamage": {
            "min": 20,
            "max": 33
        },
        "moveCost": 6,
        "attackCost": 6,
        "droplistID": "droplist_light_18",
        "spawnGroup": "light_drow",
        "faction": "drow_elf"
    },
    {
        "id": "light_drow_19",
        "name": "Light Drow Priestess",
        "iconID": "monsters_arulirs:1",
        "maxHP": 517,
        "attackChance": 85,
        "attackDamage": {
            "min": 5,
            "max": 15
        },
        "moveCost": 7,
        "attackCost": 5,
        "droplistID": "droplist_light_19",
        "spawnGroup": "light_drow",
        "faction": "drow_elf"
    },
    {
        "id": "light_drow_20",
        "name": "Light Drow Executioner",
        "iconID": "monsters_arulirs:1",
        "maxHP": 191,
        "attackChance": 56,
        "attackDamage": {
            "min": 10,
            "max": 24
        },
        "moveCost": 5,
        "attackCost": 6,
        "droplistID": "droplist_light_20",
        "spawnGroup": "light_drow",
        "faction": "drow_elf"
    },
    {
        "id": "light_drow_21",
        "name": "Light Drow Webspinner",
        "iconID": "monsters_arulirs:1",
        "maxHP": 404,
        "attackChance": 48,
        "attackDamage": {
            "min": 11,
            "max": 38
        },
        "moveCost": 4,
        "attackCost": 7,
        "droplistID": "droplist_light_21",
        "spawnGroup": "light_drow",
        "faction": "drow_elf"
    },
    {
        "id": "light_drow_22",
        "name": "Light Drow Sorcerer",
        "iconID": "monsters_arulirs:1",
        "maxHP": 569,
        "attackChance": 79,
        "attackDamage": {
            "min": 16,
            "max": 42
        },
        "moveCost": 6,
        "attackCost": 6,
        "droplistID": "droplist_light_22",
        "spawnGroup": "light_drow",
        "faction": "drow_elf"
    },
    {
        "id": "light_drow_23",
        "name": "Light Drow Knight",
        "iconID": "monsters_arulirs:1",
        "maxHP": 542,
        "attackChance": 62,
        "attackDamage": {
            "min": 14,
            "max": 30
        },
        "moveCost": 6,
        "attackCost": 4,
        "droplistID": "droplist_light_23",
        "spawnGroup": "light_drow",
        "faction": "drow_elf"
    },
    {
        "id": "light_drow_24",
        "name": "Light Drow Assassin",
        "iconID": "monsters_arulirs:1",
        "maxHP": 475,
        "attackChance": 71,
        "attackDamage": {
            "min": 14,
            "max": 30
        },
        "moveCost": 3,
        "attackCost": 7,
        "droplistID": "droplist_light_24",
        "spawnGroup": "light_drow",
        "faction": "drow_elf"
    },
    {
        "id": "light_drow_25",
        "name": "Light Drow Raider",
        "iconID": "monsters_arulirs:1",
        "maxHP": 273,
        "attackChance": 56,
        "attackDamage": {
            "min": 11,
            "max": 39
        },
        "moveCost": 8,
        "attackCost": 7,
        "droplistID": "droplist_light_25",
        "spawnGroup": "light_drow",
        "faction": "drow_elf"
    }
]